{"identifier":{"interfaceLanguage":"swift","url":"doc:\/\/com.apple.Swift\/documentation\/Swift\/Array\/lexicographicallyPrecedes(_:by:)"},"kind":"symbol","hierarchy":{"paths":[["doc:\/\/com.apple.Swift\/documentation\/Swift","doc:\/\/com.apple.Swift\/documentation\/Swift\/Array"]]},"sections":[],"abstract":[{"text":"Returns a Boolean value indicating whether the sequence precedes another","type":"text"},{"text":" ","type":"text"},{"text":"sequence in a lexicographical (dictionary) ordering, using the given","type":"text"},{"text":" ","type":"text"},{"text":"predicate to compare elements.","type":"text"}],"schemaVersion":{"minor":3,"patch":0,"major":0},"variants":[{"paths":["\/documentation\/swift\/array\/lexicographicallyprecedes(_:by:)"],"traits":[{"interfaceLanguage":"swift"}]}],"seeAlsoSections":[{"anchor":"Comparing-Arrays","generated":true,"title":"Comparing Arrays","identifiers":["doc:\/\/com.apple.Swift\/documentation\/Swift\/Array\/==(_:_:)","doc:\/\/com.apple.Swift\/documentation\/Swift\/Array\/!=(_:_:)","doc:\/\/com.apple.Swift\/documentation\/Swift\/Array\/elementsEqual(_:)","doc:\/\/com.apple.Swift\/documentation\/Swift\/Array\/elementsEqual(_:by:)","doc:\/\/com.apple.Swift\/documentation\/Swift\/Array\/starts(with:)","doc:\/\/com.apple.Swift\/documentation\/Swift\/Array\/starts(with:by:)","doc:\/\/com.apple.Swift\/documentation\/Swift\/Array\/lexicographicallyPrecedes(_:)"]}],"primaryContentSections":[{"declarations":[{"languages":["swift"],"tokens":[{"text":"func","kind":"keyword"},{"text":" ","kind":"text"},{"text":"lexicographicallyPrecedes","kind":"identifier"},{"text":"<","kind":"text"},{"text":"OtherSequence","kind":"genericParameter"},{"text":">(","kind":"text"},{"text":"_","kind":"externalParam"},{"text":" ","kind":"text"},{"text":"other","kind":"internalParam"},{"text":": ","kind":"text"},{"text":"OtherSequence","kind":"typeIdentifier","preciseIdentifier":"s:STsE25lexicographicallyPrecedes_2bySbqd___Sb7ElementQz_ADtKXEtKSTRd__ACQyd__ADRSlF13OtherSequenceL_qd__mfp"},{"text":", ","kind":"text"},{"text":"by","kind":"externalParam"},{"text":" ","kind":"text"},{"text":"areInIncreasingOrder","kind":"internalParam"},{"text":": (","kind":"text"},{"text":"Element","kind":"typeIdentifier","preciseIdentifier":"s:ST7ElementQa","identifier":"doc:\/\/com.apple.Swift\/documentation\/Swift\/Sequence\/Element"},{"text":", ","kind":"text"},{"text":"Element","kind":"typeIdentifier","preciseIdentifier":"s:ST7ElementQa","identifier":"doc:\/\/com.apple.Swift\/documentation\/Swift\/Sequence\/Element"},{"text":") ","kind":"text"},{"text":"throws","kind":"keyword"},{"text":" -> ","kind":"text"},{"text":"Bool","kind":"typeIdentifier","preciseIdentifier":"s:Sb","identifier":"doc:\/\/com.apple.Swift\/documentation\/Swift\/Bool"},{"text":") ","kind":"text"},{"text":"rethrows","kind":"keyword"},{"text":" -> ","kind":"text"},{"text":"Bool","kind":"typeIdentifier","preciseIdentifier":"s:Sb","identifier":"doc:\/\/com.apple.Swift\/documentation\/Swift\/Bool"},{"text":" ","kind":"text"},{"text":"where","kind":"keyword"},{"text":" ","kind":"text"},{"text":"OtherSequence","kind":"typeIdentifier"},{"text":" : ","kind":"text"},{"text":"Sequence","kind":"typeIdentifier","preciseIdentifier":"s:ST","identifier":"doc:\/\/com.apple.Swift\/documentation\/Swift\/Sequence"},{"text":", ","kind":"text"},{"text":"Self","kind":"typeIdentifier"},{"text":".","kind":"text"},{"text":"Element","kind":"typeIdentifier","preciseIdentifier":"s:ST7ElementQa","identifier":"doc:\/\/com.apple.Swift\/documentation\/Swift\/Sequence\/Element"},{"text":" == ","kind":"text"},{"text":"OtherSequence","kind":"typeIdentifier"},{"text":".","kind":"text"},{"text":"Element","kind":"typeIdentifier","preciseIdentifier":"s:ST7ElementQa","identifier":"doc:\/\/com.apple.Swift\/documentation\/Swift\/Sequence\/Element"}],"platforms":["macOS"]}],"kind":"declarations"},{"kind":"parameters","parameters":[{"content":[{"inlineContent":[{"type":"text","text":"A sequence to compare to this sequence."}],"type":"paragraph"}],"name":"other"},{"content":[{"inlineContent":[{"type":"text","text":"A predicate that returns "},{"code":"true","type":"codeVoice"},{"type":"text","text":" if its first"},{"type":"text","text":" "},{"type":"text","text":"argument should be ordered before its second argument; otherwise,"},{"type":"text","text":" "},{"code":"false","type":"codeVoice"},{"type":"text","text":"."}],"type":"paragraph"}],"name":"areInIncreasingOrder"}]},{"kind":"content","content":[{"text":"Return Value","level":2,"anchor":"return-value","type":"heading"},{"inlineContent":[{"text":"","type":"text"},{"type":"codeVoice","code":"true"},{"text":" if this sequence precedes ","type":"text"},{"type":"codeVoice","code":"other"},{"text":" in a dictionary","type":"text"},{"text":" ","type":"text"},{"text":"ordering as ordered by ","type":"text"},{"type":"codeVoice","code":"areInIncreasingOrder"},{"text":"; otherwise, ","type":"text"},{"type":"codeVoice","code":"false"},{"text":".","type":"text"}],"type":"paragraph"}]},{"kind":"content","content":[{"text":"Discussion","level":2,"anchor":"discussion","type":"heading"},{"inlineContent":[{"text":"The predicate must be a ","type":"text"},{"inlineContent":[{"type":"text","text":"strict weak ordering"}],"type":"emphasis"},{"text":" over the elements. That","type":"text"},{"text":" ","type":"text"},{"text":"is, for any elements ","type":"text"},{"type":"codeVoice","code":"a"},{"text":", ","type":"text"},{"type":"codeVoice","code":"b"},{"text":", and ","type":"text"},{"type":"codeVoice","code":"c"},{"text":", the following conditions must","type":"text"},{"text":" ","type":"text"},{"text":"hold:","type":"text"}],"type":"paragraph"},{"items":[{"content":[{"inlineContent":[{"code":"areInIncreasingOrder(a, a)","type":"codeVoice"},{"text":" is always ","type":"text"},{"code":"false","type":"codeVoice"},{"text":". (Irreflexivity)","type":"text"}],"type":"paragraph"}]},{"content":[{"inlineContent":[{"text":"If ","type":"text"},{"code":"areInIncreasingOrder(a, b)","type":"codeVoice"},{"text":" and ","type":"text"},{"code":"areInIncreasingOrder(b, c)","type":"codeVoice"},{"text":" are","type":"text"},{"text":" ","type":"text"},{"text":"both ","type":"text"},{"code":"true","type":"codeVoice"},{"text":", then ","type":"text"},{"code":"areInIncreasingOrder(a, c)","type":"codeVoice"},{"text":" is also","type":"text"},{"text":" ","type":"text"},{"code":"true","type":"codeVoice"},{"text":". (Transitive comparability)","type":"text"}],"type":"paragraph"}]},{"content":[{"inlineContent":[{"text":"Two elements are ","type":"text"},{"inlineContent":[{"text":"incomparable","type":"text"}],"type":"emphasis"},{"text":" if neither is ordered before the other","type":"text"},{"text":" ","type":"text"},{"text":"according to the predicate. If ","type":"text"},{"code":"a","type":"codeVoice"},{"text":" and ","type":"text"},{"code":"b","type":"codeVoice"},{"text":" are incomparable, and ","type":"text"},{"code":"b","type":"codeVoice"},{"text":" ","type":"text"},{"text":"and ","type":"text"},{"code":"c","type":"codeVoice"},{"text":" are incomparable, then ","type":"text"},{"code":"a","type":"codeVoice"},{"type":"text","text":" and "},{"type":"codeVoice","code":"c"},{"type":"text","text":" are also incomparable."},{"type":"text","text":" "},{"text":"(Transitive incomparability)","type":"text"}],"type":"paragraph"}]}],"type":"unorderedList"},{"style":"note","name":"Note","type":"aside","content":[{"inlineContent":[{"type":"text","text":"This method implements the mathematical notion of lexicographical"},{"text":" ","type":"text"},{"type":"text","text":"ordering, which has no connection to Unicode.  If you are sorting"},{"type":"text","text":" "},{"type":"text","text":"strings to present to the end user, use "},{"code":"String","type":"codeVoice"},{"type":"text","text":" APIs that perform"},{"type":"text","text":" "},{"type":"text","text":"localized comparison instead."}],"type":"paragraph"}]},{"content":[{"inlineContent":[{"text":"O(","type":"text"},{"inlineContent":[{"text":"m","type":"text"}],"type":"emphasis"},{"type":"text","text":"), where "},{"inlineContent":[{"text":"m","type":"text"}],"type":"emphasis"},{"text":" is the lesser of the length of the","type":"text"},{"text":" ","type":"text"},{"text":"sequence and the length of ","type":"text"},{"code":"other","type":"codeVoice"},{"type":"text","text":"."}],"type":"paragraph"}],"type":"aside","style":"note","name":"Complexity"}]}],"metadata":{"modules":[{"name":"Swift"}],"role":"symbol","platforms":[{"deprecated":false,"name":"iOS","unavailable":false,"beta":false,"introducedAt":"8.0"},{"deprecated":false,"name":"iPadOS","unavailable":false,"beta":false,"introducedAt":"8.0"},{"deprecated":false,"name":"Mac Catalyst","unavailable":false,"beta":false,"introducedAt":"13.0"},{"deprecated":false,"name":"macOS","unavailable":false,"beta":false,"introducedAt":"10.10"},{"deprecated":false,"name":"tvOS","unavailable":false,"beta":false,"introducedAt":"9.0"},{"deprecated":false,"name":"visionOS","unavailable":false,"beta":false,"introducedAt":"1.0"},{"deprecated":false,"name":"watchOS","unavailable":false,"beta":false,"introducedAt":"2.0"}],"roleHeading":"Instance Method","symbolKind":"method","fragments":[{"text":"func","kind":"keyword"},{"text":" ","kind":"text"},{"text":"lexicographicallyPrecedes","kind":"identifier"},{"text":"<","kind":"text"},{"text":"OtherSequence","kind":"genericParameter"},{"text":">(","kind":"text"},{"text":"OtherSequence","preciseIdentifier":"s:STsE25lexicographicallyPrecedes_2bySbqd___Sb7ElementQz_ADtKXEtKSTRd__ACQyd__ADRSlF13OtherSequenceL_qd__mfp","kind":"typeIdentifier"},{"text":", ","kind":"text"},{"text":"by","kind":"externalParam"},{"text":": (","kind":"text"},{"text":"Element","preciseIdentifier":"s:ST7ElementQa","kind":"typeIdentifier"},{"text":", ","kind":"text"},{"text":"Element","preciseIdentifier":"s:ST7ElementQa","kind":"typeIdentifier"},{"text":") ","kind":"text"},{"text":"throws","kind":"keyword"},{"text":" -> ","kind":"text"},{"text":"Bool","preciseIdentifier":"s:Sb","kind":"typeIdentifier"},{"text":") ","kind":"text"},{"text":"rethrows","kind":"keyword"},{"text":" -> ","kind":"text"},{"text":"Bool","preciseIdentifier":"s:Sb","kind":"typeIdentifier"}],"title":"lexicographicallyPrecedes(_:by:)","externalID":"s:STsE25lexicographicallyPrecedes_2bySbqd___Sb7ElementQz_ADtKXEtKSTRd__ACQyd__ADRSlF::SYNTHESIZED::s:Sa","extendedModule":"Swift"},"references":{"doc://com.apple.Swift/documentation/Swift/Array/lexicographicallyPrecedes(_:by:)":{"role":"symbol","abstract":[{"type":"text","text":"Returns a Boolean value indicating whether the sequence precedes another"},{"type":"text","text":" "},{"type":"text","text":"sequence in a lexicographical (dictionary) ordering, using the given"},{"type":"text","text":" "},{"type":"text","text":"predicate to compare elements."}],"url":"\/documentation\/swift\/array\/lexicographicallyprecedes(_:by:)","title":"lexicographicallyPrecedes(_:by:)","fragments":[{"kind":"keyword","text":"func"},{"kind":"text","text":" "},{"kind":"identifier","text":"lexicographicallyPrecedes"},{"kind":"text","text":"<"},{"kind":"genericParameter","text":"OtherSequence"},{"kind":"text","text":">("},{"preciseIdentifier":"s:STsE25lexicographicallyPrecedes_2bySbqd___Sb7ElementQz_ADtKXEtKSTRd__ACQyd__ADRSlF13OtherSequenceL_qd__mfp","kind":"typeIdentifier","text":"OtherSequence"},{"kind":"text","text":", "},{"kind":"externalParam","text":"by"},{"kind":"text","text":": ("},{"preciseIdentifier":"s:ST7ElementQa","kind":"typeIdentifier","text":"Element"},{"kind":"text","text":", "},{"preciseIdentifier":"s:ST7ElementQa","kind":"typeIdentifier","text":"Element"},{"kind":"text","text":") "},{"kind":"keyword","text":"throws"},{"kind":"text","text":" -> "},{"preciseIdentifier":"s:Sb","kind":"typeIdentifier","text":"Bool"},{"kind":"text","text":") "},{"kind":"keyword","text":"rethrows"},{"kind":"text","text":" -> "},{"preciseIdentifier":"s:Sb","kind":"typeIdentifier","text":"Bool"}],"type":"topic","identifier":"doc:\/\/com.apple.Swift\/documentation\/Swift\/Array\/lexicographicallyPrecedes(_:by:)","kind":"symbol"},"doc://com.apple.Swift/documentation/Swift":{"role":"collection","url":"\/documentation\/swift","identifier":"doc:\/\/com.apple.Swift\/documentation\/Swift","type":"topic","title":"Swift","images":[{"identifier":"Swift-PageImage-card.png","type":"card"}],"kind":"symbol","abstract":[{"type":"text","text":"Build apps using a powerful open language."}]},"doc://com.apple.Swift/documentation/Swift/Sequence":{"title":"Sequence","url":"\/documentation\/swift\/sequence","type":"topic","abstract":[{"type":"text","text":"A type that provides sequential, iterated access to its elements."}],"kind":"symbol","role":"symbol","identifier":"doc:\/\/com.apple.Swift\/documentation\/Swift\/Sequence","fragments":[{"kind":"keyword","text":"protocol"},{"kind":"text","text":" "},{"kind":"identifier","text":"Sequence"}],"navigatorTitle":[{"kind":"identifier","text":"Sequence"}]},"doc://com.apple.Swift/documentation/Swift/Array/elementsEqual(_:by:)":{"role":"symbol","abstract":[{"text":"Returns a Boolean value indicating whether this sequence and another","type":"text"},{"text":" ","type":"text"},{"text":"sequence contain equivalent elements in the same order, using the given","type":"text"},{"text":" ","type":"text"},{"text":"predicate as the equivalence test.","type":"text"}],"url":"\/documentation\/swift\/array\/elementsequal(_:by:)","title":"elementsEqual(_:by:)","fragments":[{"kind":"keyword","text":"func"},{"kind":"text","text":" "},{"kind":"identifier","text":"elementsEqual"},{"kind":"text","text":"<"},{"text":"OtherSequence","kind":"genericParameter"},{"text":">(","kind":"text"},{"text":"OtherSequence","kind":"typeIdentifier","preciseIdentifier":"s:STsE13elementsEqual_2bySbqd___Sb7ElementQz_ACQyd__tKXEtKSTRd__lF13OtherSequenceL_qd__mfp"},{"text":", ","kind":"text"},{"text":"by","kind":"externalParam"},{"text":": (","kind":"text"},{"text":"Element","kind":"typeIdentifier","preciseIdentifier":"s:ST7ElementQa"},{"text":", ","kind":"text"},{"preciseIdentifier":"s:STsE13elementsEqual_2bySbqd___Sb7ElementQz_ACQyd__tKXEtKSTRd__lF13OtherSequenceL_qd__mfp","kind":"typeIdentifier","text":"OtherSequence"},{"text":".","kind":"text"},{"text":"Element","kind":"typeIdentifier","preciseIdentifier":"s:ST7ElementQa"},{"text":") ","kind":"text"},{"text":"throws","kind":"keyword"},{"text":" -> ","kind":"text"},{"text":"Bool","kind":"typeIdentifier","preciseIdentifier":"s:Sb"},{"text":") ","kind":"text"},{"text":"rethrows","kind":"keyword"},{"kind":"text","text":" -> "},{"text":"Bool","kind":"typeIdentifier","preciseIdentifier":"s:Sb"}],"type":"topic","identifier":"doc:\/\/com.apple.Swift\/documentation\/Swift\/Array\/elementsEqual(_:by:)","kind":"symbol"},"doc://com.apple.Swift/documentation/Swift/Array/lexicographicallyPrecedes(_:)":{"role":"symbol","conformance":{"availabilityPrefix":[{"text":"Available when","type":"text"}],"conformancePrefix":[{"text":"Conforms when","type":"text"}],"constraints":[{"type":"codeVoice","code":"Element"},{"text":" conforms to ","type":"text"},{"type":"codeVoice","code":"Comparable"},{"text":".","type":"text"}]},"abstract":[{"text":"Returns a Boolean value indicating whether the sequence precedes another","type":"text"},{"text":" ","type":"text"},{"text":"sequence in a lexicographical (dictionary) ordering, using the","type":"text"},{"text":" ","type":"text"},{"text":"less-than operator (","type":"text"},{"type":"codeVoice","code":"<"},{"text":") to compare elements.","type":"text"}],"url":"\/documentation\/swift\/array\/lexicographicallyprecedes(_:)","title":"lexicographicallyPrecedes(_:)","fragments":[{"kind":"keyword","text":"func"},{"kind":"text","text":" "},{"kind":"identifier","text":"lexicographicallyPrecedes"},{"kind":"text","text":"<"},{"kind":"genericParameter","text":"OtherSequence"},{"kind":"text","text":">("},{"preciseIdentifier":"s:STsSL7ElementRpzrlE25lexicographicallyPrecedesySbqd__STRd__AAQyd__ABRSlF13OtherSequenceL_qd__mfp","kind":"typeIdentifier","text":"OtherSequence"},{"kind":"text","text":") -> "},{"preciseIdentifier":"s:Sb","kind":"typeIdentifier","text":"Bool"}],"type":"topic","identifier":"doc:\/\/com.apple.Swift\/documentation\/Swift\/Array\/lexicographicallyPrecedes(_:)","kind":"symbol"},"doc://com.apple.Swift/documentation/Swift/Array/==(_:_:)":{"fragments":[{"kind":"keyword","text":"static"},{"kind":"text","text":" "},{"text":"func","kind":"keyword"},{"kind":"text","text":" "},{"kind":"identifier","text":"=="},{"kind":"text","text":" "},{"kind":"text","text":"("},{"kind":"typeIdentifier","preciseIdentifier":"s:Sa","text":"Array"},{"text":"<","kind":"text"},{"kind":"typeIdentifier","preciseIdentifier":"s:SasSQRzlE7Elementxmfp","text":"Element"},{"text":">, ","kind":"text"},{"preciseIdentifier":"s:Sa","kind":"typeIdentifier","text":"Array"},{"text":"<","kind":"text"},{"text":"Element","kind":"typeIdentifier","preciseIdentifier":"s:SasSQRzlE7Elementxmfp"},{"text":">) -> ","kind":"text"},{"text":"Bool","kind":"typeIdentifier","preciseIdentifier":"s:Sb"}],"url":"\/documentation\/swift\/array\/==(_:_:)","role":"symbol","conformance":{"constraints":[{"type":"codeVoice","code":"Element"},{"text":" conforms to ","type":"text"},{"type":"codeVoice","code":"Equatable"},{"text":".","type":"text"}],"availabilityPrefix":[{"text":"Available when","type":"text"}],"conformancePrefix":[{"text":"Conforms when","type":"text"}]},"kind":"symbol","type":"topic","identifier":"doc:\/\/com.apple.Swift\/documentation\/Swift\/Array\/==(_:_:)","title":"==(_:_:)","abstract":[{"text":"Returns a Boolean value indicating whether two arrays contain the same","type":"text"},{"text":" ","type":"text"},{"text":"elements in the same order.","type":"text"}]},"doc://com.apple.Swift/documentation/Swift/Array":{"title":"Array","url":"\/documentation\/swift\/array","type":"topic","abstract":[{"type":"text","text":"An ordered, random-access collection."}],"kind":"symbol","role":"symbol","identifier":"doc:\/\/com.apple.Swift\/documentation\/Swift\/Array","fragments":[{"kind":"keyword","text":"struct"},{"text":" ","kind":"text"},{"text":"Array","kind":"identifier"}],"navigatorTitle":[{"text":"Array","kind":"identifier"}]},"doc://com.apple.Swift/documentation/Swift/Sequence/Element":{"title":"Element","url":"\/documentation\/swift\/sequence\/element","type":"topic","required":true,"abstract":[{"type":"text","text":"A type representing the sequence’s elements."}],"kind":"symbol","role":"symbol","identifier":"doc:\/\/com.apple.Swift\/documentation\/Swift\/Sequence\/Element","fragments":[{"text":"associatedtype","kind":"keyword"},{"text":" ","kind":"text"},{"text":"Element","kind":"identifier"}]},"doc://com.apple.Swift/documentation/Swift/Array/!=(_:_:)":{"url":"\/documentation\/swift\/array\/!=(_:_:)","identifier":"doc:\/\/com.apple.Swift\/documentation\/Swift\/Array\/!=(_:_:)","role":"symbol","fragments":[{"kind":"keyword","text":"static"},{"kind":"text","text":" "},{"kind":"keyword","text":"func"},{"kind":"text","text":" "},{"kind":"identifier","text":"!="},{"kind":"text","text":" "},{"kind":"text","text":"("},{"kind":"typeIdentifier","text":"Self"},{"kind":"text","text":", "},{"kind":"typeIdentifier","text":"Self"},{"kind":"text","text":") -> "},{"kind":"typeIdentifier","preciseIdentifier":"s:Sb","text":"Bool"}],"abstract":[{"text":"Returns a Boolean value indicating whether two values are not equal.","type":"text"}],"title":"!=(_:_:)","type":"topic","kind":"symbol"},"doc://com.apple.Swift/documentation/Swift/Array/elementsEqual(_:)":{"role":"symbol","conformance":{"availabilityPrefix":[{"text":"Available when","type":"text"}],"conformancePrefix":[{"text":"Conforms when","type":"text"}],"constraints":[{"type":"codeVoice","code":"Element"},{"text":" conforms to ","type":"text"},{"type":"codeVoice","code":"Equatable"},{"type":"text","text":"."}]},"abstract":[{"text":"Returns a Boolean value indicating whether this sequence and another","type":"text"},{"text":" ","type":"text"},{"text":"sequence contain the same elements in the same order.","type":"text"}],"url":"\/documentation\/swift\/array\/elementsequal(_:)","title":"elementsEqual(_:)","fragments":[{"kind":"keyword","text":"func"},{"text":" ","kind":"text"},{"kind":"identifier","text":"elementsEqual"},{"text":"<","kind":"text"},{"text":"OtherSequence","kind":"genericParameter"},{"text":">(","kind":"text"},{"text":"OtherSequence","kind":"typeIdentifier","preciseIdentifier":"s:STsSQ7ElementRpzrlE13elementsEqualySbqd__STRd__AAQyd__ABRSlF13OtherSequenceL_qd__mfp"},{"text":") -> ","kind":"text"},{"preciseIdentifier":"s:Sb","kind":"typeIdentifier","text":"Bool"}],"type":"topic","identifier":"doc:\/\/com.apple.Swift\/documentation\/Swift\/Array\/elementsEqual(_:)","kind":"symbol"},"doc://com.apple.Swift/documentation/Swift/Bool":{"role":"symbol","fragments":[{"kind":"keyword","text":"struct"},{"kind":"text","text":" "},{"kind":"identifier","text":"Bool"}],"url":"\/documentation\/swift\/bool","identifier":"doc:\/\/com.apple.Swift\/documentation\/Swift\/Bool","navigatorTitle":[{"kind":"identifier","text":"Bool"}],"type":"topic","title":"Bool","kind":"symbol","abstract":[{"text":"A value type whose instances are either ","type":"text"},{"type":"codeVoice","code":"true"},{"type":"text","text":" or "},{"type":"codeVoice","code":"false"},{"text":".","type":"text"}]},"doc://com.apple.Swift/documentation/Swift/Array/starts(with:)":{"role":"symbol","conformance":{"availabilityPrefix":[{"text":"Available when","type":"text"}],"constraints":[{"type":"codeVoice","code":"Element"},{"text":" conforms to ","type":"text"},{"type":"codeVoice","code":"Equatable"},{"text":".","type":"text"}],"conformancePrefix":[{"text":"Conforms when","type":"text"}]},"abstract":[{"text":"Returns a Boolean value indicating whether the initial elements of the","type":"text"},{"text":" ","type":"text"},{"text":"sequence are the same as the elements in another sequence.","type":"text"}],"url":"\/documentation\/swift\/array\/starts(with:)","title":"starts(with:)","fragments":[{"kind":"keyword","text":"func"},{"kind":"text","text":" "},{"kind":"identifier","text":"starts"},{"kind":"text","text":"<"},{"kind":"genericParameter","text":"PossiblePrefix"},{"kind":"text","text":">("},{"kind":"externalParam","text":"with"},{"kind":"text","text":": "},{"kind":"typeIdentifier","text":"PossiblePrefix","preciseIdentifier":"s:STsSQ7ElementRpzrlE6starts4withSbqd___tSTRd__AAQyd__ABRSlF14PossiblePrefixL_qd__mfp"},{"kind":"text","text":") -> "},{"kind":"typeIdentifier","text":"Bool","preciseIdentifier":"s:Sb"}],"type":"topic","identifier":"doc:\/\/com.apple.Swift\/documentation\/Swift\/Array\/starts(with:)","kind":"symbol"},"doc://com.apple.Swift/documentation/Swift/Array/starts(with:by:)":{"role":"symbol","abstract":[{"text":"Returns a Boolean value indicating whether the initial elements of the","type":"text"},{"type":"text","text":" "},{"type":"text","text":"sequence are equivalent to the elements in another sequence, using"},{"text":" ","type":"text"},{"type":"text","text":"the given predicate as the equivalence test."}],"url":"\/documentation\/swift\/array\/starts(with:by:)","title":"starts(with:by:)","fragments":[{"text":"func","kind":"keyword"},{"kind":"text","text":" "},{"kind":"identifier","text":"starts"},{"text":"<","kind":"text"},{"text":"PossiblePrefix","kind":"genericParameter"},{"text":">(","kind":"text"},{"text":"with","kind":"externalParam"},{"text":": ","kind":"text"},{"kind":"typeIdentifier","text":"PossiblePrefix","preciseIdentifier":"s:STsE6starts4with2bySbqd___Sb7ElementQz_ADQyd__tKXEtKSTRd__lF14PossiblePrefixL_qd__mfp"},{"text":", ","kind":"text"},{"kind":"externalParam","text":"by"},{"text":": (","kind":"text"},{"kind":"typeIdentifier","text":"Element","preciseIdentifier":"s:ST7ElementQa"},{"text":", ","kind":"text"},{"preciseIdentifier":"s:STsE6starts4with2bySbqd___Sb7ElementQz_ADQyd__tKXEtKSTRd__lF14PossiblePrefixL_qd__mfp","kind":"typeIdentifier","text":"PossiblePrefix"},{"kind":"text","text":"."},{"preciseIdentifier":"s:ST7ElementQa","kind":"typeIdentifier","text":"Element"},{"kind":"text","text":") "},{"text":"throws","kind":"keyword"},{"text":" -> ","kind":"text"},{"text":"Bool","kind":"typeIdentifier","preciseIdentifier":"s:Sb"},{"text":") ","kind":"text"},{"text":"rethrows","kind":"keyword"},{"text":" -> ","kind":"text"},{"text":"Bool","kind":"typeIdentifier","preciseIdentifier":"s:Sb"}],"type":"topic","identifier":"doc:\/\/com.apple.Swift\/documentation\/Swift\/Array\/starts(with:by:)","kind":"symbol"},"Swift-PageImage-card.png":{"identifier":"Swift-PageImage-card.png","type":"image","variants":[{"traits":["2x","light"],"url":"\/images\/com.apple.Swift\/Swift-PageImage-card@2x.png"},{"traits":["2x","dark"],"url":"\/images\/com.apple.Swift\/Swift-PageImage-card~dark@2x.png"}],"alt":"An orange Swift logo on a gradient background."}}}