{"sections":[],"hierarchy":{"paths":[["doc:\/\/com.apple.Swift\/documentation\/Swift","doc:\/\/com.apple.Swift\/documentation\/Swift\/AsyncThrowingMapSequence"]]},"identifier":{"interfaceLanguage":"swift","url":"doc:\/\/com.apple.Swift\/documentation\/Swift\/AsyncThrowingMapSequence\/compactMap(_:)-1rx1n"},"primaryContentSections":[{"kind":"declarations","declarations":[{"languages":["swift"],"tokens":[{"kind":"attribute","text":"@preconcurrency"},{"kind":"text","text":" "},{"kind":"keyword","text":"func"},{"kind":"text","text":" "},{"kind":"identifier","text":"compactMap"},{"kind":"text","text":"<"},{"kind":"genericParameter","text":"ElementOfResult"},{"kind":"text","text":">("},{"kind":"externalParam","text":"_"},{"kind":"text","text":" "},{"kind":"internalParam","text":"transform"},{"kind":"text","text":": "},{"kind":"attribute","text":"@Sendable"},{"kind":"text","text":" "},{"kind":"attribute","text":"@escaping"},{"kind":"text","text":" ("},{"kind":"typeIdentifier","text":"Element","identifier":"doc:\/\/com.apple.Swift\/documentation\/Swift\/AsyncSequence\/Element","preciseIdentifier":"s:Sci7ElementQa"},{"kind":"text","text":") "},{"kind":"keyword","text":"async"},{"kind":"text","text":" "},{"kind":"keyword","text":"throws"},{"kind":"text","text":" -> "},{"kind":"typeIdentifier","text":"ElementOfResult","preciseIdentifier":"s:Sci12_ConcurrencyE10compactMapyAA020AsyncThrowingCompactC8SequenceVyxqd__Gqd__Sg7ElementQzYaKclF0H8OfResultL_qd__mfp"},{"kind":"text","text":"?) -> "},{"kind":"typeIdentifier","text":"AsyncThrowingCompactMapSequence","identifier":"doc:\/\/com.apple.Swift\/documentation\/Swift\/AsyncThrowingCompactMapSequence","preciseIdentifier":"s:12_Concurrency31AsyncThrowingCompactMapSequenceV"},{"kind":"text","text":"<"},{"kind":"typeIdentifier","text":"Self"},{"kind":"text","text":", "},{"kind":"typeIdentifier","text":"ElementOfResult","preciseIdentifier":"s:Sci12_ConcurrencyE10compactMapyAA020AsyncThrowingCompactC8SequenceVyxqd__Gqd__Sg7ElementQzYaKclF0H8OfResultL_qd__mfp"},{"kind":"text","text":">"}],"platforms":["macOS"]}]},{"kind":"parameters","parameters":[{"content":[{"inlineContent":[{"type":"text","text":"An error-throwing mapping closure. "},{"type":"codeVoice","code":"transform"},{"type":"text","text":" "},{"type":"text","text":"accepts an element of this sequence as its parameter and returns a"},{"type":"text","text":" "},{"type":"text","text":"transformed value of the same or of a different type. If "},{"type":"codeVoice","code":"transform"},{"type":"text","text":" "},{"type":"text","text":"throws an error, the sequence ends."}],"type":"paragraph"}],"name":"transform"}]},{"kind":"content","content":[{"level":2,"anchor":"return-value","text":"Return Value","type":"heading"},{"inlineContent":[{"text":"An asynchronous sequence that contains, in order, the","type":"text"},{"text":" ","type":"text"},{"text":"non-","type":"text"},{"code":"nil","type":"codeVoice"},{"text":" elements produced by the ","type":"text"},{"code":"transform","type":"codeVoice"},{"text":" closure. The sequence","type":"text"},{"text":" ","type":"text"},{"text":"ends either when the base sequence ends or when ","type":"text"},{"code":"transform","type":"codeVoice"},{"text":" throws an","type":"text"},{"text":" ","type":"text"},{"text":"error.","type":"text"}],"type":"paragraph"}]},{"kind":"content","content":[{"level":2,"anchor":"discussion","text":"Discussion","type":"heading"},{"inlineContent":[{"text":"Use the ","type":"text"},{"code":"compactMap(_:)","type":"codeVoice"},{"text":" method to transform every element received from","type":"text"},{"text":" ","type":"text"},{"text":"a base asynchronous sequence, while also discarding any ","type":"text"},{"code":"nil","type":"codeVoice"},{"text":" results","type":"text"},{"text":" ","type":"text"},{"text":"from the closure. Typically, you use this to transform from one type of","type":"text"},{"text":" ","type":"text"},{"text":"element to another.","type":"text"}],"type":"paragraph"},{"inlineContent":[{"text":"In this example, an asynchronous sequence called ","type":"text"},{"code":"Counter","type":"codeVoice"},{"text":" produces ","type":"text"},{"code":"Int","type":"codeVoice"},{"text":" ","type":"text"},{"text":"values from ","type":"text"},{"code":"1","type":"codeVoice"},{"text":" to ","type":"text"},{"code":"5","type":"codeVoice"},{"text":". The closure provided to the ","type":"text"},{"code":"compactMap(_:)","type":"codeVoice"},{"text":" ","type":"text"},{"text":"method takes each ","type":"text"},{"code":"Int","type":"codeVoice"},{"text":" and looks up a corresponding ","type":"text"},{"code":"String","type":"codeVoice"},{"text":" from a","type":"text"},{"text":" ","type":"text"},{"code":"romanNumeralDict","type":"codeVoice"},{"text":" dictionary. Since there is no key for ","type":"text"},{"code":"4","type":"codeVoice"},{"text":", the closure","type":"text"},{"text":" ","type":"text"},{"text":"returns ","type":"text"},{"code":"nil","type":"codeVoice"},{"text":" in this case, which ","type":"text"},{"code":"compactMap(_:)","type":"codeVoice"},{"text":" omits from the","type":"text"},{"text":" ","type":"text"},{"text":"transformed asynchronous sequence. When the value is ","type":"text"},{"code":"5","type":"codeVoice"},{"text":", the closure","type":"text"},{"text":" ","type":"text"},{"text":"throws ","type":"text"},{"code":"MyError","type":"codeVoice"},{"text":", terminating the sequence.","type":"text"}],"type":"paragraph"},{"code":["let romanNumeralDict: [Int: String] =","    [1: \"I\", 2: \"II\", 3: \"III\", 5: \"V\"]","","do {","    let stream = Counter(howHigh: 5)","        .compactMap { (value) throws -> String? in","            if value == 5 {","                throw MyError()","            }","            return romanNumeralDict[value]","        }","    for try await numeral in stream {","        print(numeral, terminator: \" \")","    }","} catch {","    print(\"Error: \\(error)\")","}","\/\/ Prints \"I II III Error: MyError() \""],"type":"codeListing","syntax":"swift"}]}],"variants":[{"paths":["\/documentation\/swift\/asyncthrowingmapsequence\/compactmap(_:)-1rx1n"],"traits":[{"interfaceLanguage":"swift"}]}],"abstract":[{"text":"Creates an asynchronous sequence that maps an error-throwing closure over","type":"text"},{"text":" ","type":"text"},{"text":"the base sequence’s elements, omitting results that don’t return a value.","type":"text"}],"schemaVersion":{"minor":3,"patch":0,"major":0},"metadata":{"symbolKind":"method","externalID":"s:Sci12_ConcurrencyE10compactMapyAA020AsyncThrowingCompactC8SequenceVyxqd__Gqd__Sg7ElementQzYaKclF::SYNTHESIZED::s:12_Concurrency24AsyncThrowingMapSequenceV","role":"symbol","fragments":[{"text":"func","kind":"keyword"},{"text":" ","kind":"text"},{"text":"compactMap","kind":"identifier"},{"text":"<","kind":"text"},{"text":"ElementOfResult","kind":"genericParameter"},{"text":">(","kind":"text"},{"text":"@Sendable","kind":"attribute"},{"text":" (","kind":"text"},{"text":"Element","kind":"typeIdentifier","preciseIdentifier":"s:Sci7ElementQa"},{"text":") ","kind":"text"},{"text":"async","kind":"keyword"},{"text":" ","kind":"text"},{"text":"throws","kind":"keyword"},{"text":" -> ","kind":"text"},{"text":"ElementOfResult","kind":"typeIdentifier","preciseIdentifier":"s:Sci12_ConcurrencyE10compactMapyAA020AsyncThrowingCompactC8SequenceVyxqd__Gqd__Sg7ElementQzYaKclF0H8OfResultL_qd__mfp"},{"text":"?) -> ","kind":"text"},{"text":"AsyncThrowingCompactMapSequence","kind":"typeIdentifier","preciseIdentifier":"s:12_Concurrency31AsyncThrowingCompactMapSequenceV"},{"text":"<","kind":"text"},{"text":"Self","kind":"typeIdentifier"},{"text":", ","kind":"text"},{"text":"ElementOfResult","kind":"typeIdentifier","preciseIdentifier":"s:Sci12_ConcurrencyE10compactMapyAA020AsyncThrowingCompactC8SequenceVyxqd__Gqd__Sg7ElementQzYaKclF0H8OfResultL_qd__mfp"},{"text":">","kind":"text"}],"roleHeading":"Instance Method","title":"compactMap(_:)","extendedModule":"_Concurrency","modules":[{"name":"Swift","relatedModules":[]}],"platforms":[{"introducedAt":"8.0","name":"iOS","beta":false,"deprecated":false,"unavailable":false},{"introducedAt":"8.0","name":"iPadOS","beta":false,"deprecated":false,"unavailable":false},{"introducedAt":"13.0","name":"Mac Catalyst","beta":false,"deprecated":false,"unavailable":false},{"introducedAt":"10.10","name":"macOS","beta":false,"deprecated":false,"unavailable":false},{"introducedAt":"9.0","name":"tvOS","beta":false,"deprecated":false,"unavailable":false},{"introducedAt":"1.0","name":"visionOS","beta":false,"deprecated":false,"unavailable":false},{"introducedAt":"2.0","name":"watchOS","beta":false,"deprecated":false,"unavailable":false}]},"kind":"symbol","references":{"doc://com.apple.Swift/documentation/Swift/AsyncThrowingCompactMapSequence":{"url":"\/documentation\/swift\/asyncthrowingcompactmapsequence","abstract":[{"text":"An asynchronous sequence that maps an error-throwing closure over the base","type":"text"},{"text":" ","type":"text"},{"text":"sequence’s elements, omitting results that don’t return a value.","type":"text"}],"title":"AsyncThrowingCompactMapSequence","kind":"symbol","identifier":"doc:\/\/com.apple.Swift\/documentation\/Swift\/AsyncThrowingCompactMapSequence","navigatorTitle":[{"text":"AsyncThrowingCompactMapSequence","kind":"identifier"}],"fragments":[{"text":"struct","kind":"keyword"},{"text":" ","kind":"text"},{"text":"AsyncThrowingCompactMapSequence","kind":"identifier"}],"type":"topic","role":"symbol"},"doc://com.apple.Swift/documentation/Swift/AsyncThrowingMapSequence/compactMap(_:)-1rx1n":{"role":"symbol","fragments":[{"kind":"keyword","text":"func"},{"kind":"text","text":" "},{"kind":"identifier","text":"compactMap"},{"kind":"text","text":"<"},{"kind":"genericParameter","text":"ElementOfResult"},{"kind":"text","text":">("},{"kind":"attribute","text":"@Sendable"},{"kind":"text","text":" ("},{"kind":"typeIdentifier","text":"Element","preciseIdentifier":"s:Sci7ElementQa"},{"kind":"text","text":") "},{"kind":"keyword","text":"async"},{"kind":"text","text":" "},{"kind":"keyword","text":"throws"},{"kind":"text","text":" -> "},{"kind":"typeIdentifier","text":"ElementOfResult","preciseIdentifier":"s:Sci12_ConcurrencyE10compactMapyAA020AsyncThrowingCompactC8SequenceVyxqd__Gqd__Sg7ElementQzYaKclF0H8OfResultL_qd__mfp"},{"kind":"text","text":"?) -> "},{"kind":"typeIdentifier","text":"AsyncThrowingCompactMapSequence","preciseIdentifier":"s:12_Concurrency31AsyncThrowingCompactMapSequenceV"},{"kind":"text","text":"<"},{"kind":"typeIdentifier","text":"Self"},{"kind":"text","text":", "},{"kind":"typeIdentifier","text":"ElementOfResult","preciseIdentifier":"s:Sci12_ConcurrencyE10compactMapyAA020AsyncThrowingCompactC8SequenceVyxqd__Gqd__Sg7ElementQzYaKclF0H8OfResultL_qd__mfp"},{"kind":"text","text":">"}],"url":"\/documentation\/swift\/asyncthrowingmapsequence\/compactmap(_:)-1rx1n","identifier":"doc:\/\/com.apple.Swift\/documentation\/Swift\/AsyncThrowingMapSequence\/compactMap(_:)-1rx1n","type":"topic","title":"compactMap(_:)","kind":"symbol","abstract":[{"text":"Creates an asynchronous sequence that maps an error-throwing closure over","type":"text"},{"text":" ","type":"text"},{"text":"the base sequence’s elements, omitting results that don’t return a value.","type":"text"}]},"doc://com.apple.Swift/documentation/Swift/AsyncSequence/Element":{"url":"\/documentation\/swift\/asyncsequence\/element","abstract":[{"text":"The type of element produced by this asynchronous sequence.","type":"text"}],"title":"Element","kind":"symbol","identifier":"doc:\/\/com.apple.Swift\/documentation\/Swift\/AsyncSequence\/Element","required":true,"fragments":[{"text":"associatedtype","kind":"keyword"},{"text":" ","kind":"text"},{"text":"Element","kind":"identifier"}],"type":"topic","role":"symbol"},"Swift-PageImage-card.png":{"variants":[{"traits":["2x","light"],"url":"\/images\/com.apple.Swift\/Swift-PageImage-card@2x.png"},{"traits":["2x","dark"],"url":"\/images\/com.apple.Swift\/Swift-PageImage-card~dark@2x.png"}],"type":"image","identifier":"Swift-PageImage-card.png","alt":"An orange Swift logo on a gradient background."},"doc://com.apple.Swift/documentation/Swift":{"role":"collection","url":"\/documentation\/swift","identifier":"doc:\/\/com.apple.Swift\/documentation\/Swift","type":"topic","title":"Swift","images":[{"identifier":"Swift-PageImage-card.png","type":"card"}],"kind":"symbol","abstract":[{"type":"text","text":"Build apps using a powerful open language."}]},"doc://com.apple.Swift/documentation/Swift/AsyncThrowingMapSequence":{"url":"\/documentation\/swift\/asyncthrowingmapsequence","abstract":[{"type":"text","text":"An asynchronous sequence that maps the given error-throwing closure over the"},{"type":"text","text":" "},{"text":"asynchronous sequence’s elements.","type":"text"}],"title":"AsyncThrowingMapSequence","kind":"symbol","identifier":"doc:\/\/com.apple.Swift\/documentation\/Swift\/AsyncThrowingMapSequence","navigatorTitle":[{"text":"AsyncThrowingMapSequence","kind":"identifier"}],"fragments":[{"text":"struct","kind":"keyword"},{"text":" ","kind":"text"},{"text":"AsyncThrowingMapSequence","kind":"identifier"}],"type":"topic","role":"symbol"}}}